{
	"frames": {
		"BalloonTug_00025.png": {
			"frame": {
				"x": 1,
				"y": 1,
				"w": 287,
				"h": 277
			},
			"rotated": false,
			"trimmed": true,
			"spriteSourceSize": {
				"x": 93,
				"y": 80,
				"w": 287,
				"h": 277
			},
			"sourceSize": {
				"w": 512,
				"h": 512
			}
		},
		"BalloonTug_00026.png": {
			"frame": {
				"x": 290,
				"y": 1,
				"w": 287,
				"h": 277
			},
			"rotated": false,
			"trimmed": true,
			"spriteSourceSize": {
				"x": 93,
				"y": 80,
				"w": 287,
				"h": 277
			},
			"sourceSize": {
				"w": 512,
				"h": 512
			}
		},
		"BalloonTug_00027.png": {
			"frame": {
				"x": 1,
				"y": 280,
				"w": 286,
				"h": 276
			},
			"rotated": false,
			"trimmed": true,
			"spriteSourceSize": {
				"x": 93,
				"y": 81,
				"w": 286,
				"h": 276
			},
			"sourceSize": {
				"w": 512,
				"h": 512
			}
		},
		"BalloonTug_00028.png": {
			"frame": {
				"x": 577,
				"y": 523,
				"w": 285,
				"h": 276
			},
			"rotated": false,
			"trimmed": true,
			"spriteSourceSize": {
				"x": 93,
				"y": 81,
				"w": 285,
				"h": 276
			},
			"sourceSize": {
				"w": 512,
				"h": 512
			}
		},
		"BalloonTug_00029.png": {
			"frame": {
				"x": 1153,
				"y": 746,
				"w": 284,
				"h": 275
			},
			"rotated": false,
			"trimmed": true,
			"spriteSourceSize": {
				"x": 93,
				"y": 82,
				"w": 284,
				"h": 275
			},
			"sourceSize": {
				"w": 512,
				"h": 512
			}
		},
		"BalloonTug_00030.png": {
			"frame": {
				"x": 576,
				"y": 801,
				"w": 283,
				"h": 275
			},
			"rotated": false,
			"trimmed": true,
			"spriteSourceSize": {
				"x": 93,
				"y": 82,
				"w": 283,
				"h": 275
			},
			"sourceSize": {
				"w": 512,
				"h": 512
			}
		},
		"BalloonTug_00031.png": {
			"frame": {
				"x": 288,
				"y": 833,
				"w": 283,
				"h": 275
			},
			"rotated": false,
			"trimmed": true,
			"spriteSourceSize": {
				"x": 93,
				"y": 82,
				"w": 283,
				"h": 275
			},
			"sourceSize": {
				"w": 512,
				"h": 512
			}
		},
		"BalloonTug_00032.png": {
			"frame": {
				"x": 573,
				"y": 1078,
				"w": 282,
				"h": 275
			},
			"rotated": false,
			"trimmed": true,
			"spriteSourceSize": {
				"x": 93,
				"y": 82,
				"w": 282,
				"h": 275
			},
			"sourceSize": {
				"w": 512,
				"h": 512
			}
		},
		"BalloonTug_00033.png": {
			"frame": {
				"x": 286,
				"y": 1110,
				"w": 282,
				"h": 275
			},
			"rotated": false,
			"trimmed": true,
			"spriteSourceSize": {
				"x": 93,
				"y": 82,
				"w": 282,
				"h": 275
			},
			"sourceSize": {
				"w": 512,
				"h": 512
			}
		},
		"BalloonTug_00034.png": {
			"frame": {
				"x": 1,
				"y": 1332,
				"w": 282,
				"h": 275
			},
			"rotated": false,
			"trimmed": true,
			"spriteSourceSize": {
				"x": 93,
				"y": 82,
				"w": 282,
				"h": 275
			},
			"sourceSize": {
				"w": 512,
				"h": 512
			}
		},
		"BalloonTug_00035.png": {
			"frame": {
				"x": 1439,
				"y": 747,
				"w": 282,
				"h": 275
			},
			"rotated": false,
			"trimmed": true,
			"spriteSourceSize": {
				"x": 93,
				"y": 82,
				"w": 282,
				"h": 275
			},
			"sourceSize": {
				"w": 512,
				"h": 512
			}
		},
		"BalloonTug_00036.png": {
			"frame": {
				"x": 1439,
				"y": 747,
				"w": 282,
				"h": 275
			},
			"rotated": false,
			"trimmed": true,
			"spriteSourceSize": {
				"x": 93,
				"y": 82,
				"w": 282,
				"h": 275
			},
			"sourceSize": {
				"w": 512,
				"h": 512
			}
		},
		"BalloonTug_00037.png": {
			"frame": {
				"x": 1439,
				"y": 747,
				"w": 282,
				"h": 275
			},
			"rotated": false,
			"trimmed": true,
			"spriteSourceSize": {
				"x": 93,
				"y": 82,
				"w": 282,
				"h": 275
			},
			"sourceSize": {
				"w": 512,
				"h": 512
			}
		},
		"BalloonTug_00038.png": {
			"frame": {
				"x": 1146,
				"y": 1023,
				"w": 282,
				"h": 275
			},
			"rotated": false,
			"trimmed": true,
			"spriteSourceSize": {
				"x": 93,
				"y": 82,
				"w": 282,
				"h": 275
			},
			"sourceSize": {
				"w": 512,
				"h": 512
			}
		},
		"BalloonTug_00039.png": {
			"frame": {
				"x": 857,
				"y": 1285,
				"w": 282,
				"h": 275
			},
			"rotated": false,
			"trimmed": true,
			"spriteSourceSize": {
				"x": 93,
				"y": 82,
				"w": 282,
				"h": 275
			},
			"sourceSize": {
				"w": 512,
				"h": 512
			}
		},
		"BalloonTug_00040.png": {
			"frame": {
				"x": 857,
				"y": 1285,
				"w": 282,
				"h": 275
			},
			"rotated": false,
			"trimmed": true,
			"spriteSourceSize": {
				"x": 93,
				"y": 82,
				"w": 282,
				"h": 275
			},
			"sourceSize": {
				"w": 512,
				"h": 512
			}
		},
		"BalloonTug_00041.png": {
			"frame": {
				"x": 857,
				"y": 1285,
				"w": 282,
				"h": 275
			},
			"rotated": false,
			"trimmed": true,
			"spriteSourceSize": {
				"x": 93,
				"y": 82,
				"w": 282,
				"h": 275
			},
			"sourceSize": {
				"w": 512,
				"h": 512
			}
		},
		"BalloonTug_00042.png": {
			"frame": {
				"x": 570,
				"y": 1355,
				"w": 282,
				"h": 275
			},
			"rotated": false,
			"trimmed": true,
			"spriteSourceSize": {
				"x": 93,
				"y": 82,
				"w": 282,
				"h": 275
			},
			"sourceSize": {
				"w": 512,
				"h": 512
			}
		},
		"BalloonTug_00043.png": {
			"frame": {
				"x": 285,
				"y": 1387,
				"w": 282,
				"h": 275
			},
			"rotated": false,
			"trimmed": true,
			"spriteSourceSize": {
				"x": 93,
				"y": 82,
				"w": 282,
				"h": 275
			},
			"sourceSize": {
				"w": 512,
				"h": 512
			}
		},
		"BalloonTug_00044.png": {
			"frame": {
				"x": 1,
				"y": 1609,
				"w": 282,
				"h": 275
			},
			"rotated": false,
			"trimmed": true,
			"spriteSourceSize": {
				"x": 93,
				"y": 82,
				"w": 282,
				"h": 275
			},
			"sourceSize": {
				"w": 512,
				"h": 512
			}
		},
		"BalloonTug_00045.png": {
			"frame": {
				"x": 1430,
				"y": 1024,
				"w": 282,
				"h": 275
			},
			"rotated": false,
			"trimmed": true,
			"spriteSourceSize": {
				"x": 93,
				"y": 82,
				"w": 282,
				"h": 275
			},
			"sourceSize": {
				"w": 512,
				"h": 512
			}
		},
		"BalloonTug_00046.png": {
			"frame": {
				"x": 1141,
				"y": 1300,
				"w": 282,
				"h": 275
			},
			"rotated": false,
			"trimmed": true,
			"spriteSourceSize": {
				"x": 93,
				"y": 82,
				"w": 282,
				"h": 275
			},
			"sourceSize": {
				"w": 512,
				"h": 512
			}
		},
		"BalloonTug_00047.png": {
			"frame": {
				"x": 854,
				"y": 1562,
				"w": 282,
				"h": 275
			},
			"rotated": false,
			"trimmed": true,
			"spriteSourceSize": {
				"x": 93,
				"y": 82,
				"w": 282,
				"h": 275
			},
			"sourceSize": {
				"w": 512,
				"h": 512
			}
		},
		"BalloonTug_00048.png": {
			"frame": {
				"x": 569,
				"y": 1632,
				"w": 282,
				"h": 275
			},
			"rotated": false,
			"trimmed": true,
			"spriteSourceSize": {
				"x": 93,
				"y": 82,
				"w": 282,
				"h": 275
			},
			"sourceSize": {
				"w": 512,
				"h": 512
			}
		},
		"BalloonTug_00049.png": {
			"frame": {
				"x": 569,
				"y": 1632,
				"w": 282,
				"h": 275
			},
			"rotated": false,
			"trimmed": true,
			"spriteSourceSize": {
				"x": 93,
				"y": 82,
				"w": 282,
				"h": 275
			},
			"sourceSize": {
				"w": 512,
				"h": 512
			}
		},
		"BalloonTug_00050.png": {
			"frame": {
				"x": 569,
				"y": 1632,
				"w": 282,
				"h": 275
			},
			"rotated": false,
			"trimmed": true,
			"spriteSourceSize": {
				"x": 93,
				"y": 82,
				"w": 282,
				"h": 275
			},
			"sourceSize": {
				"w": 512,
				"h": 512
			}
		},
		"BalloonTug_00051.png": {
			"frame": {
				"x": 285,
				"y": 1664,
				"w": 282,
				"h": 275
			},
			"rotated": false,
			"trimmed": true,
			"spriteSourceSize": {
				"x": 93,
				"y": 82,
				"w": 282,
				"h": 275
			},
			"sourceSize": {
				"w": 512,
				"h": 512
			}
		},
		"BalloonTug_00052.png": {
			"frame": {
				"x": 285,
				"y": 1664,
				"w": 282,
				"h": 275
			},
			"rotated": false,
			"trimmed": true,
			"spriteSourceSize": {
				"x": 93,
				"y": 82,
				"w": 282,
				"h": 275
			},
			"sourceSize": {
				"w": 512,
				"h": 512
			}
		},
		"BalloonTug_00053.png": {
			"frame": {
				"x": 1,
				"y": 1886,
				"w": 282,
				"h": 275
			},
			"rotated": false,
			"trimmed": true,
			"spriteSourceSize": {
				"x": 93,
				"y": 82,
				"w": 282,
				"h": 275
			},
			"sourceSize": {
				"w": 512,
				"h": 512
			}
		},
		"BalloonTug_00054.png": {
			"frame": {
				"x": 1425,
				"y": 1301,
				"w": 282,
				"h": 275
			},
			"rotated": false,
			"trimmed": true,
			"spriteSourceSize": {
				"x": 93,
				"y": 82,
				"w": 282,
				"h": 275
			},
			"sourceSize": {
				"w": 512,
				"h": 512
			}
		},
		"BalloonTug_00055.png": {
			"frame": {
				"x": 1425,
				"y": 1301,
				"w": 282,
				"h": 275
			},
			"rotated": false,
			"trimmed": true,
			"spriteSourceSize": {
				"x": 93,
				"y": 82,
				"w": 282,
				"h": 275
			},
			"sourceSize": {
				"w": 512,
				"h": 512
			}
		},
		"BalloonTug_00056.png": {
			"frame": {
				"x": 1425,
				"y": 1301,
				"w": 282,
				"h": 275
			},
			"rotated": false,
			"trimmed": true,
			"spriteSourceSize": {
				"x": 93,
				"y": 82,
				"w": 282,
				"h": 275
			},
			"sourceSize": {
				"w": 512,
				"h": 512
			}
		},
		"BalloonTug_00057.png": {
			"frame": {
				"x": 1425,
				"y": 1301,
				"w": 282,
				"h": 275
			},
			"rotated": false,
			"trimmed": true,
			"spriteSourceSize": {
				"x": 93,
				"y": 82,
				"w": 282,
				"h": 275
			},
			"sourceSize": {
				"w": 512,
				"h": 512
			}
		},
		"BalloonTug_00058.png": {
			"frame": {
				"x": 1138,
				"y": 1577,
				"w": 282,
				"h": 275
			},
			"rotated": false,
			"trimmed": true,
			"spriteSourceSize": {
				"x": 93,
				"y": 82,
				"w": 282,
				"h": 275
			},
			"sourceSize": {
				"w": 512,
				"h": 512
			}
		},
		"BalloonTug_00059.png": {
			"frame": {
				"x": 1138,
				"y": 1577,
				"w": 282,
				"h": 275
			},
			"rotated": false,
			"trimmed": true,
			"spriteSourceSize": {
				"x": 93,
				"y": 82,
				"w": 282,
				"h": 275
			},
			"sourceSize": {
				"w": 512,
				"h": 512
			}
		},
		"BalloonTug_00060.png": {
			"frame": {
				"x": 1138,
				"y": 1577,
				"w": 282,
				"h": 275
			},
			"rotated": false,
			"trimmed": true,
			"spriteSourceSize": {
				"x": 93,
				"y": 82,
				"w": 282,
				"h": 275
			},
			"sourceSize": {
				"w": 512,
				"h": 512
			}
		},
		"BalloonTug_00061.png": {
			"frame": {
				"x": 1138,
				"y": 1577,
				"w": 282,
				"h": 275
			},
			"rotated": false,
			"trimmed": true,
			"spriteSourceSize": {
				"x": 93,
				"y": 82,
				"w": 282,
				"h": 275
			},
			"sourceSize": {
				"w": 512,
				"h": 512
			}
		},
		"BalloonTug_00062.png": {
			"frame": {
				"x": 853,
				"y": 1839,
				"w": 282,
				"h": 275
			},
			"rotated": false,
			"trimmed": true,
			"spriteSourceSize": {
				"x": 93,
				"y": 82,
				"w": 282,
				"h": 275
			},
			"sourceSize": {
				"w": 512,
				"h": 512
			}
		},
		"BalloonTug_00063.png": {
			"frame": {
				"x": 853,
				"y": 1839,
				"w": 282,
				"h": 275
			},
			"rotated": false,
			"trimmed": true,
			"spriteSourceSize": {
				"x": 93,
				"y": 82,
				"w": 282,
				"h": 275
			},
			"sourceSize": {
				"w": 512,
				"h": 512
			}
		},
		"BalloonTug_00064.png": {
			"frame": {
				"x": 853,
				"y": 1839,
				"w": 282,
				"h": 275
			},
			"rotated": false,
			"trimmed": true,
			"spriteSourceSize": {
				"x": 93,
				"y": 82,
				"w": 282,
				"h": 275
			},
			"sourceSize": {
				"w": 512,
				"h": 512
			}
		},
		"BalloonTug_00065.png": {
			"frame": {
				"x": 569,
				"y": 1909,
				"w": 282,
				"h": 275
			},
			"rotated": false,
			"trimmed": true,
			"spriteSourceSize": {
				"x": 93,
				"y": 82,
				"w": 282,
				"h": 275
			},
			"sourceSize": {
				"w": 512,
				"h": 512
			}
		},
		"BalloonTug_00066.png": {
			"frame": {
				"x": 569,
				"y": 1909,
				"w": 282,
				"h": 275
			},
			"rotated": false,
			"trimmed": true,
			"spriteSourceSize": {
				"x": 93,
				"y": 82,
				"w": 282,
				"h": 275
			},
			"sourceSize": {
				"w": 512,
				"h": 512
			}
		},
		"BalloonTug_00067.png": {
			"frame": {
				"x": 569,
				"y": 1909,
				"w": 282,
				"h": 275
			},
			"rotated": false,
			"trimmed": true,
			"spriteSourceSize": {
				"x": 93,
				"y": 82,
				"w": 282,
				"h": 275
			},
			"sourceSize": {
				"w": 512,
				"h": 512
			}
		},
		"BalloonTug_00068.png": {
			"frame": {
				"x": 569,
				"y": 1909,
				"w": 282,
				"h": 275
			},
			"rotated": false,
			"trimmed": true,
			"spriteSourceSize": {
				"x": 93,
				"y": 82,
				"w": 282,
				"h": 275
			},
			"sourceSize": {
				"w": 512,
				"h": 512
			}
		},
		"BalloonTug_00069.png": {
			"frame": {
				"x": 853,
				"y": 2116,
				"w": 282,
				"h": 275
			},
			"rotated": true,
			"trimmed": true,
			"spriteSourceSize": {
				"x": 93,
				"y": 82,
				"w": 282,
				"h": 275
			},
			"sourceSize": {
				"w": 512,
				"h": 512
			}
		},
		"BalloonTug_00070.png": {
			"frame": {
				"x": 853,
				"y": 2116,
				"w": 282,
				"h": 275
			},
			"rotated": true,
			"trimmed": true,
			"spriteSourceSize": {
				"x": 93,
				"y": 82,
				"w": 282,
				"h": 275
			},
			"sourceSize": {
				"w": 512,
				"h": 512
			}
		},
		"BalloonTug_00071.png": {
			"frame": {
				"x": 853,
				"y": 2116,
				"w": 282,
				"h": 275
			},
			"rotated": true,
			"trimmed": true,
			"spriteSourceSize": {
				"x": 93,
				"y": 82,
				"w": 282,
				"h": 275
			},
			"sourceSize": {
				"w": 512,
				"h": 512
			}
		},
		"BalloonTug_00072.png": {
			"frame": {
				"x": 853,
				"y": 2116,
				"w": 282,
				"h": 275
			},
			"rotated": true,
			"trimmed": true,
			"spriteSourceSize": {
				"x": 93,
				"y": 82,
				"w": 282,
				"h": 275
			},
			"sourceSize": {
				"w": 512,
				"h": 512
			}
		},
		"BalloonTug_00073.png": {
			"frame": {
				"x": 1130,
				"y": 2116,
				"w": 282,
				"h": 275
			},
			"rotated": true,
			"trimmed": true,
			"spriteSourceSize": {
				"x": 93,
				"y": 82,
				"w": 282,
				"h": 275
			},
			"sourceSize": {
				"w": 512,
				"h": 512
			}
		},
		"BalloonTug_00074.png": {
			"frame": {
				"x": 1130,
				"y": 2116,
				"w": 282,
				"h": 275
			},
			"rotated": true,
			"trimmed": true,
			"spriteSourceSize": {
				"x": 93,
				"y": 82,
				"w": 282,
				"h": 275
			},
			"sourceSize": {
				"w": 512,
				"h": 512
			}
		},
		"BalloonTug_00075.png": {
			"frame": {
				"x": 1130,
				"y": 2116,
				"w": 282,
				"h": 275
			},
			"rotated": true,
			"trimmed": true,
			"spriteSourceSize": {
				"x": 93,
				"y": 82,
				"w": 282,
				"h": 275
			},
			"sourceSize": {
				"w": 512,
				"h": 512
			}
		},
		"BalloonTug_00076.png": {
			"frame": {
				"x": 1714,
				"y": 1133,
				"w": 280,
				"h": 272
			},
			"rotated": false,
			"trimmed": true,
			"spriteSourceSize": {
				"x": 93,
				"y": 85,
				"w": 280,
				"h": 272
			},
			"sourceSize": {
				"w": 512,
				"h": 512
			}
		},
		"BalloonTug_00077.png": {
			"frame": {
				"x": 1735,
				"y": 566,
				"w": 283,
				"h": 254
			},
			"rotated": true,
			"trimmed": true,
			"spriteSourceSize": {
				"x": 93,
				"y": 103,
				"w": 283,
				"h": 254
			},
			"sourceSize": {
				"w": 512,
				"h": 512
			}
		},
		"BalloonTug_00078.png": {
			"frame": {
				"x": 1,
				"y": 810,
				"w": 285,
				"h": 243
			},
			"rotated": false,
			"trimmed": true,
			"spriteSourceSize": {
				"x": 93,
				"y": 114,
				"w": 285,
				"h": 243
			},
			"sourceSize": {
				"w": 512,
				"h": 512
			}
		},
		"BalloonTug_00079.png": {
			"frame": {
				"x": 865,
				"y": 514,
				"w": 286,
				"h": 236
			},
			"rotated": false,
			"trimmed": true,
			"spriteSourceSize": {
				"x": 93,
				"y": 121,
				"w": 286,
				"h": 236
			},
			"sourceSize": {
				"w": 512,
				"h": 512
			}
		},
		"BalloonTug_00080.png": {
			"frame": {
				"x": 1157,
				"y": 278,
				"w": 287,
				"h": 233
			},
			"rotated": false,
			"trimmed": true,
			"spriteSourceSize": {
				"x": 93,
				"y": 124,
				"w": 287,
				"h": 233
			},
			"sourceSize": {
				"w": 512,
				"h": 512
			}
		},
		"BalloonTug_00081.png": {
			"frame": {
				"x": 1157,
				"y": 513,
				"w": 287,
				"h": 231
			},
			"rotated": false,
			"trimmed": true,
			"spriteSourceSize": {
				"x": 93,
				"y": 126,
				"w": 287,
				"h": 231
			},
			"sourceSize": {
				"w": 512,
				"h": 512
			}
		},
		"BalloonTug_00082.png": {
			"frame": {
				"x": 1446,
				"y": 514,
				"w": 287,
				"h": 231
			},
			"rotated": false,
			"trimmed": true,
			"spriteSourceSize": {
				"x": 93,
				"y": 126,
				"w": 287,
				"h": 231
			},
			"sourceSize": {
				"w": 512,
				"h": 512
			}
		},
		"BalloonTug_00083.png": {
			"frame": {
				"x": 868,
				"y": 279,
				"w": 287,
				"h": 233
			},
			"rotated": false,
			"trimmed": true,
			"spriteSourceSize": {
				"x": 93,
				"y": 124,
				"w": 287,
				"h": 233
			},
			"sourceSize": {
				"w": 512,
				"h": 512
			}
		},
		"BalloonTug_00084.png": {
			"frame": {
				"x": 1446,
				"y": 276,
				"w": 287,
				"h": 236
			},
			"rotated": false,
			"trimmed": true,
			"spriteSourceSize": {
				"x": 93,
				"y": 121,
				"w": 287,
				"h": 236
			},
			"sourceSize": {
				"w": 512,
				"h": 512
			}
		},
		"BalloonTug_00085.png": {
			"frame": {
				"x": 577,
				"y": 280,
				"w": 286,
				"h": 241
			},
			"rotated": false,
			"trimmed": true,
			"spriteSourceSize": {
				"x": 93,
				"y": 116,
				"w": 286,
				"h": 241
			},
			"sourceSize": {
				"w": 512,
				"h": 512
			}
		},
		"BalloonTug_00086.png": {
			"frame": {
				"x": 1,
				"y": 558,
				"w": 285,
				"h": 250
			},
			"rotated": false,
			"trimmed": true,
			"spriteSourceSize": {
				"x": 93,
				"y": 107,
				"w": 285,
				"h": 250
			},
			"sourceSize": {
				"w": 512,
				"h": 512
			}
		},
		"BalloonTug_00087.png": {
			"frame": {
				"x": 864,
				"y": 752,
				"w": 284,
				"h": 260
			},
			"rotated": false,
			"trimmed": true,
			"spriteSourceSize": {
				"x": 93,
				"y": 97,
				"w": 284,
				"h": 260
			},
			"sourceSize": {
				"w": 512,
				"h": 512
			}
		},
		"BalloonTug_00088.png": {
			"frame": {
				"x": 861,
				"y": 1014,
				"w": 283,
				"h": 269
			},
			"rotated": false,
			"trimmed": true,
			"spriteSourceSize": {
				"x": 93,
				"y": 88,
				"w": 283,
				"h": 269
			},
			"sourceSize": {
				"w": 512,
				"h": 512
			}
		},
		"BalloonTug_00089.png": {
			"frame": {
				"x": 1422,
				"y": 1578,
				"w": 280,
				"h": 272
			},
			"rotated": false,
			"trimmed": true,
			"spriteSourceSize": {
				"x": 93,
				"y": 85,
				"w": 280,
				"h": 272
			},
			"sourceSize": {
				"w": 512,
				"h": 512
			}
		},
		"BalloonTug_00090.png": {
			"frame": {
				"x": 1735,
				"y": 282,
				"w": 282,
				"h": 255
			},
			"rotated": true,
			"trimmed": true,
			"spriteSourceSize": {
				"x": 93,
				"y": 102,
				"w": 282,
				"h": 255
			},
			"sourceSize": {
				"w": 512,
				"h": 512
			}
		},
		"BalloonTug_00091.png": {
			"frame": {
				"x": 1709,
				"y": 1407,
				"w": 281,
				"h": 243
			},
			"rotated": false,
			"trimmed": true,
			"spriteSourceSize": {
				"x": 93,
				"y": 114,
				"w": 281,
				"h": 243
			},
			"sourceSize": {
				"w": 512,
				"h": 512
			}
		},
		"BalloonTug_00092.png": {
			"frame": {
				"x": 1704,
				"y": 1652,
				"w": 279,
				"h": 237
			},
			"rotated": false,
			"trimmed": true,
			"spriteSourceSize": {
				"x": 93,
				"y": 120,
				"w": 279,
				"h": 237
			},
			"sourceSize": {
				"w": 512,
				"h": 512
			}
		},
		"BalloonTug_00093.png": {
			"frame": {
				"x": 280,
				"y": 2163,
				"w": 278,
				"h": 233
			},
			"rotated": false,
			"trimmed": true,
			"spriteSourceSize": {
				"x": 93,
				"y": 124,
				"w": 278,
				"h": 233
			},
			"sourceSize": {
				"w": 512,
				"h": 512
			}
		},
		"BalloonTug_00094.png": {
			"frame": {
				"x": 1137,
				"y": 1854,
				"w": 278,
				"h": 232
			},
			"rotated": false,
			"trimmed": true,
			"spriteSourceSize": {
				"x": 93,
				"y": 125,
				"w": 278,
				"h": 232
			},
			"sourceSize": {
				"w": 512,
				"h": 512
			}
		},
		"BalloonTug_00095.png": {
			"frame": {
				"x": 1686,
				"y": 2134,
				"w": 277,
				"h": 233
			},
			"rotated": false,
			"trimmed": true,
			"spriteSourceSize": {
				"x": 93,
				"y": 124,
				"w": 277,
				"h": 233
			},
			"sourceSize": {
				"w": 512,
				"h": 512
			}
		},
		"BalloonTug_00096.png": {
			"frame": {
				"x": 1,
				"y": 2163,
				"w": 277,
				"h": 235
			},
			"rotated": false,
			"trimmed": true,
			"spriteSourceSize": {
				"x": 93,
				"y": 122,
				"w": 277,
				"h": 235
			},
			"sourceSize": {
				"w": 512,
				"h": 512
			}
		},
		"BalloonTug_00097.png": {
			"frame": {
				"x": 1407,
				"y": 2102,
				"w": 277,
				"h": 237
			},
			"rotated": false,
			"trimmed": true,
			"spriteSourceSize": {
				"x": 93,
				"y": 120,
				"w": 277,
				"h": 237
			},
			"sourceSize": {
				"w": 512,
				"h": 512
			}
		},
		"BalloonTug_00098.png": {
			"frame": {
				"x": 1702,
				"y": 1891,
				"w": 277,
				"h": 241
			},
			"rotated": false,
			"trimmed": true,
			"spriteSourceSize": {
				"x": 93,
				"y": 116,
				"w": 277,
				"h": 241
			},
			"sourceSize": {
				"w": 512,
				"h": 512
			}
		},
		"BalloonTug_00099.png": {
			"frame": {
				"x": 1422,
				"y": 1852,
				"w": 278,
				"h": 248
			},
			"rotated": false,
			"trimmed": true,
			"spriteSourceSize": {
				"x": 93,
				"y": 109,
				"w": 278,
				"h": 248
			},
			"sourceSize": {
				"w": 512,
				"h": 512
			}
		},
		"BalloonTug_00100.png": {
			"frame": {
				"x": 1735,
				"y": 1,
				"w": 279,
				"h": 257
			},
			"rotated": true,
			"trimmed": true,
			"spriteSourceSize": {
				"x": 93,
				"y": 100,
				"w": 279,
				"h": 257
			},
			"sourceSize": {
				"w": 512,
				"h": 512
			}
		},
		"BalloonTug_00101.png": {
			"frame": {
				"x": 1723,
				"y": 851,
				"w": 280,
				"h": 266
			},
			"rotated": true,
			"trimmed": true,
			"spriteSourceSize": {
				"x": 93,
				"y": 91,
				"w": 280,
				"h": 266
			},
			"sourceSize": {
				"w": 512,
				"h": 512
			}
		},
		"BalloonTug_00102.png": {
			"frame": {
				"x": 1,
				"y": 1055,
				"w": 283,
				"h": 275
			},
			"rotated": false,
			"trimmed": true,
			"spriteSourceSize": {
				"x": 93,
				"y": 82,
				"w": 283,
				"h": 275
			},
			"sourceSize": {
				"w": 512,
				"h": 512
			}
		},
		"BalloonTug_00103.png": {
			"frame": {
				"x": 289,
				"y": 556,
				"w": 285,
				"h": 275
			},
			"rotated": false,
			"trimmed": true,
			"spriteSourceSize": {
				"x": 93,
				"y": 82,
				"w": 285,
				"h": 275
			},
			"sourceSize": {
				"w": 512,
				"h": 512
			}
		},
		"BalloonTug_00104.png": {
			"frame": {
				"x": 289,
				"y": 280,
				"w": 286,
				"h": 274
			},
			"rotated": false,
			"trimmed": true,
			"spriteSourceSize": {
				"x": 93,
				"y": 83,
				"w": 286,
				"h": 274
			},
			"sourceSize": {
				"w": 512,
				"h": 512
			}
		},
		"BalloonTug_00105.png": {
			"frame": {
				"x": 1446,
				"y": 1,
				"w": 287,
				"h": 273
			},
			"rotated": false,
			"trimmed": true,
			"spriteSourceSize": {
				"x": 93,
				"y": 84,
				"w": 287,
				"h": 273
			},
			"sourceSize": {
				"w": 512,
				"h": 512
			}
		},
		"BalloonTug_00106.png": {
			"frame": {
				"x": 1157,
				"y": 1,
				"w": 287,
				"h": 275
			},
			"rotated": false,
			"trimmed": true,
			"spriteSourceSize": {
				"x": 93,
				"y": 82,
				"w": 287,
				"h": 275
			},
			"sourceSize": {
				"w": 512,
				"h": 512
			}
		},
		"BalloonTug_00107.png": {
			"frame": {
				"x": 868,
				"y": 1,
				"w": 287,
				"h": 276
			},
			"rotated": false,
			"trimmed": true,
			"spriteSourceSize": {
				"x": 93,
				"y": 81,
				"w": 287,
				"h": 276
			},
			"sourceSize": {
				"w": 512,
				"h": 512
			}
		},
		"BalloonTug_00108.png": {
			"frame": {
				"x": 579,
				"y": 1,
				"w": 287,
				"h": 277
			},
			"rotated": false,
			"trimmed": true,
			"spriteSourceSize": {
				"x": 93,
				"y": 80,
				"w": 287,
				"h": 277
			},
			"sourceSize": {
				"w": 512,
				"h": 512
			}
		},
		"BalloonTug_00109.png": {
			"frame": {
				"x": 579,
				"y": 1,
				"w": 287,
				"h": 277
			},
			"rotated": false,
			"trimmed": true,
			"spriteSourceSize": {
				"x": 93,
				"y": 80,
				"w": 287,
				"h": 277
			},
			"sourceSize": {
				"w": 512,
				"h": 512
			}
		}
	},
	"animations": {
		"menu": [
			"BalloonTug_00025.png",
			"BalloonTug_00026.png",
			"BalloonTug_00027.png",
			"BalloonTug_00028.png",
			"BalloonTug_00029.png",
			"BalloonTug_00030.png",
			"BalloonTug_00031.png",
			"BalloonTug_00032.png",
			"BalloonTug_00033.png",
			"BalloonTug_00034.png",
			"BalloonTug_00035.png",
			"BalloonTug_00036.png",
			"BalloonTug_00037.png",
			"BalloonTug_00038.png",
			"BalloonTug_00039.png",
			"BalloonTug_00040.png",
			"BalloonTug_00041.png",
			"BalloonTug_00042.png",
			"BalloonTug_00043.png",
			"BalloonTug_00044.png",
			"BalloonTug_00045.png",
			"BalloonTug_00046.png",
			"BalloonTug_00047.png",
			"BalloonTug_00048.png",
			"BalloonTug_00049.png",
			"BalloonTug_00050.png",
			"BalloonTug_00051.png",
			"BalloonTug_00052.png",
			"BalloonTug_00053.png",
			"BalloonTug_00054.png",
			"BalloonTug_00055.png",
			"BalloonTug_00056.png",
			"BalloonTug_00057.png",
			"BalloonTug_00058.png",
			"BalloonTug_00059.png",
			"BalloonTug_00060.png",
			"BalloonTug_00061.png",
			"BalloonTug_00062.png",
			"BalloonTug_00063.png",
			"BalloonTug_00064.png",
			"BalloonTug_00065.png",
			"BalloonTug_00066.png",
			"BalloonTug_00067.png",
			"BalloonTug_00068.png",
			"BalloonTug_00069.png",
			"BalloonTug_00070.png",
			"BalloonTug_00071.png",
			"BalloonTug_00072.png",
			"BalloonTug_00073.png",
			"BalloonTug_00074.png",
			"BalloonTug_00075.png",
			"BalloonTug_00076.png",
			"BalloonTug_00077.png",
			"BalloonTug_00078.png",
			"BalloonTug_00079.png",
			"BalloonTug_00080.png",
			"BalloonTug_00081.png",
			"BalloonTug_00082.png",
			"BalloonTug_00083.png",
			"BalloonTug_00084.png",
			"BalloonTug_00085.png",
			"BalloonTug_00086.png",
			"BalloonTug_00087.png",
			"BalloonTug_00088.png",
			"BalloonTug_00089.png",
			"BalloonTug_00090.png",
			"BalloonTug_00091.png",
			"BalloonTug_00092.png",
			"BalloonTug_00093.png",
			"BalloonTug_00094.png",
			"BalloonTug_00095.png",
			"BalloonTug_00096.png",
			"BalloonTug_00097.png",
			"BalloonTug_00098.png",
			"BalloonTug_00099.png",
			"BalloonTug_00100.png",
			"BalloonTug_00101.png",
			"BalloonTug_00102.png",
			"BalloonTug_00103.png",
			"BalloonTug_00104.png",
			"BalloonTug_00105.png",
			"BalloonTug_00106.png",
			"BalloonTug_00107.png",
			"BalloonTug_00108.png",
			"BalloonTug_00109.png"
		]
	},
	"meta": {
		"app": "https://www.codeandweb.com/texturepacker",
		"version": "1.1",
		"image": "menu.png",
		"format": "RGBA8888",
		"size": {
			"w": 1995,
			"h": 2399
		},
		"scale": "1",
		"smartupdate": "$TexturePacker:SmartUpdate:41ccde5cab74cfbded6c3bc3bce3e0a5:31f8afc3b8863ca0b1803349e71e1c52:e1b68abd82547da08a80c89591506971$"
	}
}